leafflow/__init__.py
leafflow-0.1.0.dist-info/licenses/LICENSE
leafflow-0.1.0.dist-info/METADATA
leafflow-0.1.0.dist-info/WHEEL
leafflow-0.1.0.dist-info/top_level.txt
leafflow-0.1.0.dist-info/RECORD
