Metadata-Version: 2.4
Name: leafflow
Version: 0.1.0
Summary: Behavior Tree runtime with Python DSL for external system integration
Author-email: Leafflow Contributors <leafflow-dev@googlegroups.com>
Maintainer-email: Leafflow Contributors <leafflow-dev@googlegroups.com>
License: Apache-2.0
Project-URL: Homepage, https://github.com/leafflow-org/leafflow
Project-URL: Repository, https://github.com/leafflow-org/leafflow
Project-URL: Documentation, https://github.com/leafflow-org/leafflow/tree/main/docs
Project-URL: Issues, https://github.com/leafflow-org/leafflow/issues
Project-URL: Changelog, https://github.com/leafflow-org/leafflow/blob/main/CHANGELOG.md
Keywords: behavior-tree,workflow,orchestration,dsl,mlops,automation,decision-tree,state-machine
Classifier: Development Status :: 2 - Pre-Alpha
Classifier: Intended Audience :: Developers
Classifier: License :: OSI Approved :: Apache Software License
Classifier: Operating System :: OS Independent
Classifier: Programming Language :: Python :: 3
Classifier: Programming Language :: Python :: 3.9
Classifier: Programming Language :: Python :: 3.10
Classifier: Programming Language :: Python :: 3.11
Classifier: Programming Language :: Python :: 3.12
Classifier: Topic :: Software Development :: Libraries :: Python Modules
Classifier: Topic :: System :: Distributed Computing
Classifier: Typing :: Typed
Requires-Python: >=3.9
License-File: LICENSE
Provides-Extra: dev
Requires-Dist: pytest>=7.0; extra == "dev"
Requires-Dist: pytest-cov>=4.0; extra == "dev"
Requires-Dist: black>=23.0; extra == "dev"
Requires-Dist: ruff>=0.1.0; extra == "dev"
Requires-Dist: mypy>=1.0; extra == "dev"
Dynamic: license-file
